src/modules/data_memory.v
module data_memory (
    input wire clk,
    input wire MemWrite,
    input wire [31:0] A,
    input wire [31:0] WD,
    output wire [31:0] RD
);
    reg [31:0] memory [65535:0];

    // Read operation
    assign RD = memory[A[31:2]]; // word aligned

    // Write operation
    always @(posedge clk) begin
        if (MemWrite) begin
            memory[A[31:2]] <= WD; // word aligned
        end
    end

    integer i;
    initial begin
        //$readmemh("data_memory.mem", memory);
        for (i = 0; i < 65536; i = i + 1) begin
            memory[i] = 32'b0;
        end

        memory[0] = 0;
        memory[1] = 1;
        memory[2] = 2;
        memory[3] = 3;
        memory[4] = 4;
        memory[5] = 5;
        memory[6] = 6;
        memory[7] = 7;
        memory[8] = 8;
        memory[9] = 9;
    end
endmodule

src/modules/alu.v
module alu(
    input [3:0] ALUControl,
    input [31:0] SrcA,
    input [31:0] SrcB,
    output reg [31:0] ALUResult,
    output reg Zero
);

    reg [31:0] ResultReg;
    wire [31:0] temp, Sum;
    wire V, slt, sltu; //overflow

    assign temp = ALUControl[0] ? ~SrcB : SrcB;

    assign Sum = SrcA + temp + ALUControl[0];

    assign V = (ALUControl[0]) ? (~(SrcA[31] ^ SrcB[31]) & (SrcA[31] ^ Sum[31])) : ((SrcA[31] ^ SrcB[31]) & (~(SrcA[31] ^ Sum[31]))); 

    assign slt = (SrcA[31] == SrcB[31]) ? (SrcA < SrcB) : SrcA[31]; 

    assign sltu = SrcA < SrcB;

    always@(*)
    case(ALUControl)
        4'b0000: ResultReg <= Sum; //add
        4'b0001: ResultReg <= Sum; //sub
        4'b0010: ResultReg <= SrcA & SrcB; //and
        4'b0011: ResultReg <= SrcA | SrcB; //or
        4'b0100: ResultReg <= SrcA ^ SrcB; //xor

        4'b0101: ResultReg <= {31'b0,slt}; //slt
        4'b0110: ResultReg <= {31'b0,sltu}; // sltu
        4'b0111: ResultReg <= {SrcA[31:12],12'b0}; //lui
        4'b1000: ResultReg <= SrcA + {SrcB[31:12],12'b0}; // AUIPC
        4'b1001: ResultReg <= {SrcB[31:12],12'b0}; // LUI

        4'b1010: ResultReg <= SrcA << SrcB; // sll, slli
        4'b1011: ResultReg <= SrcA >>> SrcB; // sra
        4'b1100: ResultReg <= SrcA >> SrcB; // srl
        default:  ResultReg <= 'bx;
    endcase

    assign Zero = (ResultReg == 32'b0);
    assign ALUResult = ResultReg;
endmodule

src/modules/alu/alu_decoder.v
module alu_decoder(
    input [1:0] ALUOp,
    input [2:0] funct3,
    input funct7b5, opb5,
    output reg [3:0] ALUControl
);

wire   RtypeSub;
assign RtypeSub = funct7b5 & opb5;

always@(*) begin
    // 1111 1111 1100 0100 1010 0011 0000 0011
    case(ALUOp) // 00
      2'b00: ALUControl = 4'b0000; //addition
      2'b01: ALUControl = 4'b0001; //subtraction or auipc
      2'b10:
      
      case(funct3)//R-type 
        3'b000:    
        if (RtypeSub) ALUControl = 4'b0001; //sub
        else ALUControl = 4'b0000; //add,addi
        3'b001: ALUControl = 4'b1010; // sll, slli;
        3'b010: ALUControl = 4'b0101; //slt,slti
        3'b110: ALUControl = 4'b0011; //or,ori
        3'b111: ALUControl = 4'b0010; //and,andi
        default: ALUControl = 4'bxxx; 
      endcase
      default: ALUControl = 4'bxxxx;
    endcase
end
endmodule

src/modules/extend.v
module extend(
	input wire [31:7] Instr,
	input wire [1:0] ImmSrc, 
	output wire [31:0] ImmExt 
);
    reg [31:0] ImmExtReg;

    always@(*)
    case(ImmSrc)
        //I-type
        2'b00: ImmExtReg = {{20{Instr[31]}},Instr[31:20]};
        //S-type
        2'b01: ImmExtReg = {{20{Instr[31]}},Instr[31:25],Instr[11:7]};
        //B-type
        2'b10: ImmExtReg = {{20{Instr[31]}},Instr[7],Instr[30:25],Instr[11:8],1'b0};
        //J-type
        2'b11: ImmExtReg = {{12{Instr[31]}},Instr[19:12],Instr[20],Instr[30:21],1'b0};
        default: ImmExtReg = 32'bx; 
    endcase
   
    assign ImmExt = ImmExtReg;
endmodule

src/modules/register_file.v
module register_file (
    input wire clk,
    input wire reset,                
    input wire WE3,                  
    input wire [4:0] A1, A2, A3,  
    input wire [31:0] WD3,           
    output wire [31:0] RD1, RD2      
);

    reg [31:0] registers [31:0];
    
    // Read operations
    assign RD1 = (A1 != 0) ? registers[A1] : 32'b0; // x0 is always 0
    assign RD2 = (A2 != 0) ? registers[A2] : 32'b0; // x0 is always 0

    // Write operation
    always @(posedge clk or posedge reset) begin
        if (reset) begin
            integer i;
            for (i = 0; i < 32; i = i + 1) begin
                registers[i] <= 32'b0;
            end
            //registers[9] <= 32'd6;
        end else if (WE3 && (A3 != 0)) begin
            registers[A3] <= WD3; // x0 is read-only
        end
        $display("clk=%b WE3=%b A3=%d WD3=%h", clk, WE3, A3, WD3);
    end

endmodule

src/modules/main_decoder.v
module main_decoder(
    input [6:0] op,
    output reg RegWrite,
    output reg [1:0] ImmSrc,
    output reg ALUSrc,
    output reg MemWrite,
    output reg [1:0] ResultSrc,
    output reg Branch,
    output reg [1:0] ALUOp,
    output reg Jump
);
always @(*) begin
    case(op)
        7'b0000011: begin
            RegWrite = 1; ImmSrc = 2'b00; ALUSrc = 1; MemWrite = 0;
            ResultSrc = 2'b01; Branch = 0; ALUOp = 2'b00; // lw
            Jump = 0;
        end
        7'b0100011: begin
            RegWrite = 0; ImmSrc = 2'b01; ALUSrc = 1; MemWrite = 1;
            ResultSrc = 2'b00; Branch = 0; ALUOp = 2'b00; // sw
            Jump = 0;
        end
        7'b0110011: begin
            RegWrite = 1; ImmSrc = 2'bxx; ALUSrc = 0; MemWrite = 0;
            ResultSrc = 2'b00; Branch = 0; ALUOp = 2'b10; // R-type
            Jump = 0;
        end
        7'b1100011: begin
            RegWrite = 0; ImmSrc = 2'b10; ALUSrc = 0; MemWrite = 0;
            ResultSrc = 2'b00; Branch = 1; ALUOp = 2'b01; // beq
            Jump = 0;
        end
        7'b0010011: begin
            RegWrite = 1; ImmSrc = 2'b00; ALUSrc = 1; MemWrite = 0;
            ResultSrc = 2'b00; Branch = 0; ALUOp = 2'b10; // addi
            Jump = 0;
        end
        7'b1101111: begin
            RegWrite = 1; ImmSrc = 2'b11; ALUSrc = 1; MemWrite = 0;
            ResultSrc = 2'b10; Branch = 0; ALUOp = 2'bxx; // jal
            Jump = 1;
        end
        default: begin
            RegWrite = 0; ImmSrc = 2'b00; ALUSrc = 0; MemWrite = 0;
            ResultSrc = 2'b00; Branch = 0; ALUOp = 2'b00;
            Jump = 0;
        end
    endcase
end
endmodule

src/modules/instruction_memory.v
module instruction_memory(
    input wire [31:0] A,
    output wire [31:0] RD
);
    reg [31:0] memory [1023:0];
    assign RD = memory[A[31:2]]; // word aligned

    integer i;
    initial begin
        // Initialize memory to zero
        for (i = 0; i < 1024; i = i + 1) begin
            memory[i] = 32'b0;
        end


        // memory[0] = 32'h00300293; // addi x5, x0, 3     -> x5 = 3
        // memory[1] = 32'h0004A303; // lw   x6, 0(x9)     -> x6 = Mem[x9 + 0]
        // memory[2] = 32'h00530333; // add  x6, x6, x5    -> x6 = x6 + x5
        // memory[3] = 32'h0064A023; // sw   x6, 0(x9)     -> Mem[x9 + 0] = x6
        // memory[4] = 32'hFE001AE3; // beq  x0, x0, L0    -> if (x0 == 0) PC = PC + offset (loop para L0)

        // Programa: Soma das 10 primeiras posições da memória (endereços 0–9)

        // start
        memory[0] = 32'h00A00293; // addi t0, x0, 10
        memory[1] = 32'h00000313; // addi t1, x0, 0
        memory[2] = 32'h00000393; // addi t2, x0, 0

        // loop
        memory[3] = 32'h00028A63; // beq t0, x0, end
        memory[4] = 32'h0003AE03; // lw  t3, 0(t2)
        memory[5] = 32'h01C30333; // add t1, t1, t3
        memory[6] = 32'h00438393; // addi t2, t2, 4
        memory[7] = 32'hfff28293; // addi t0, t0, -1
        memory[8] = 32'h00000363; // beq x0, x0, loop

        // end
        memory[9] = 32'h00000013; // end: addi x0, x0, 0
        memory[10]= 32'hfc000ee3; // beq x0, x0, start

        // //start
        // 0x00A00293; // addi t0, x0, 10
        // 0x00000313; // addi t1, x0, 0
        // 0x00000393; // addi t2, x0, 0

        // //loop
        // 0x28028A63; // beq t0, x0, end (20 offset)
        // 0x000E2383; // lw  t3, 0(t2)
        // 0x01C30333; // add t1, t1, t3
        // 0x00438393; // addi t2, t2, 4
        // 0xfff28293; // addi t0, t0, -1
        // 0xfe0006e3; // beq x0, x0, loop (-20 offset)

        // //end
        // 0x00000013; // addi x0, x0, 0
        // 0xfc000ee3; // beq x0, x0, start (-36 offset)

    end

endmodule

src/modules/pc.v
module pc (	
	input wire clk,reset,
	input wire [31:0] PCNext,
	output wire [31:0] PC 
);
  reg [31:0] PCReg;

  always@(posedge clk or posedge reset) begin
	  if (reset) PCReg <= {32{1'b0}};
	  else PCReg <= PCNext;
  end	
  
  assign PC = PCReg;
endmodule

src/modules/full_pipeline.v
module full_pipeline(
    input  wire clk,
    input  wire reset
);
    wire [31:0] PC, PCNext, PCPlus4, InstrIF;

    reg  [31:0] IF_ID_PC, IF_ID_Instr;

    wire [6:0]  ID_opcode = IF_ID_Instr[6:0];
    wire [4:0]  ID_rs1    = IF_ID_Instr[19:15];
    wire [4:0]  ID_rs2    = IF_ID_Instr[24:20];
    wire [4:0]  ID_rd     = IF_ID_Instr[11:7];
    wire [2:0]  ID_funct3 = IF_ID_Instr[14:12];
    wire        ID_funct7_5 = IF_ID_Instr[30];

    wire [1:0]  ID_ALUOp;
    wire [1:0]  ID_ImmSrc;
    wire [1:0]  ID_ResultSrc;
    wire        ID_ALUSrc, ID_MemWrite, ID_RegWrite, ID_Branch;

    wire [31:0] RF_RD1, RF_RD2;
    wire [31:0] ID_ImmExt;

    reg  [31:0] ID_EX_PC, ID_EX_SrcA, ID_EX_SrcB, ID_EX_Imm;
    reg  [4:0]  ID_EX_rs1, ID_EX_rs2, ID_EX_rd;
    reg  [2:0]  ID_EX_funct3;
    reg         ID_EX_funct7_5;
    reg         ID_EX_ALUSrc, ID_EX_MemWrite, ID_EX_RegWrite, ID_EX_Branch;
    reg  [1:0]  ID_EX_ALUOp, ID_EX_ResultSrc;

    wire [3:0]  EX_ALUControl;
    wire [31:0] EX_SrcB, EX_ALUResult;
    wire        EX_Zero;
    wire [31:0] EX_BranchTarget;
    wire        EX_BranchTaken;

    reg  [31:0] EX_MEM_ALUResult, EX_MEM_WriteData, EX_MEM_BranchTarget;
    reg  [4:0]  EX_MEM_rd;
    reg         EX_MEM_MemWrite, EX_MEM_RegWrite, EX_MEM_BranchTaken;
    reg  [1:0]  EX_MEM_ResultSrc;

    wire [31:0] MEM_ReadData;
    reg  [31:0] MEM_WB_ReadData, MEM_WB_ALUResult;
    reg  [4:0]  MEM_WB_rd;
    reg         MEM_WB_RegWrite;
    reg  [1:0]  MEM_WB_ResultSrc;

    wire [31:0] WB_Result;
    assign WB_Result = (MEM_WB_ResultSrc == 2'b01) ? MEM_WB_ReadData : MEM_WB_ALUResult;

    pc pc_reg(.clk(clk), .reset(reset), .PCNext(PCNext), .PC(PC));
    instruction_memory imem(.A(PC), .RD(InstrIF));

    main_decoder md(.op(ID_opcode),
        .RegWrite(ID_RegWrite),
        .ImmSrc(ID_ImmSrc),
        .ALUSrc(ID_ALUSrc),
        .MemWrite(ID_MemWrite),
        .ResultSrc(ID_ResultSrc),
        .Branch(ID_Branch),
        .ALUOp(ID_ALUOp)
    );

    register_file rf(.clk(clk), .reset(reset), .WE3(MEM_WB_RegWrite), .A1(ID_rs1), .A2(ID_rs2), .A3(MEM_WB_rd), .WD3(WB_Result), .RD1(RF_RD1), .RD2(RF_RD2));

    extend immgen(.Instr(IF_ID_Instr[31:7]), .ImmSrc(ID_ImmSrc), .ImmExt(ID_ImmExt));

    alu_decoder ad(.ALUOp(ID_EX_ALUOp), .funct3(ID_EX_funct3), .funct7b5(ID_EX_funct7_5), .ALUControl(EX_ALUControl));

    alu alu_unit(.SrcA(ID_EX_SrcA), .SrcB(EX_SrcB), .ALUControl(EX_ALUControl), .ALUResult(EX_ALUResult), .Zero(EX_Zero));

    data_memory dmem(.clk(clk), .MemWrite(EX_MEM_MemWrite), .A(EX_MEM_ALUResult), .WD(EX_MEM_WriteData), .RD(MEM_ReadData));

    assign PCPlus4 = PC + 32'd4;
    assign EX_BranchTarget = ID_EX_PC + ID_EX_Imm;
    assign EX_BranchTaken = ID_EX_Branch & EX_Zero;

    assign PCNext = EX_BranchTaken ? EX_BranchTarget : PCPlus4;

    assign EX_SrcB = ID_EX_ALUSrc ? ID_EX_Imm : ID_EX_SrcB;

    always @(posedge clk or posedge reset) begin
        if (reset) begin
            IF_ID_PC <= 32'd0;
            IF_ID_Instr <= 32'd0;
        end else begin
            IF_ID_PC <= PC;
            IF_ID_Instr <= InstrIF;
        end
    end

    always @(posedge clk or posedge reset) begin
        if (reset) begin
            ID_EX_PC <= 0; ID_EX_SrcA <= 0; ID_EX_SrcB <= 0; ID_EX_Imm <= 0;
            ID_EX_rs1 <= 0; ID_EX_rs2 <= 0; ID_EX_rd <= 0; ID_EX_funct3 <= 0; ID_EX_funct7_5 <= 0;
            ID_EX_ALUSrc <= 0; ID_EX_MemWrite <= 0; ID_EX_RegWrite <= 0; ID_EX_Branch <= 0;
            ID_EX_ALUOp <= 0; ID_EX_ResultSrc <= 0;
        end else begin
            ID_EX_PC <= IF_ID_PC;
            ID_EX_SrcA <= RF_RD1;
            ID_EX_SrcB <= RF_RD2;
            ID_EX_Imm <= ID_ImmExt;
            ID_EX_rs1 <= ID_rs1;
            ID_EX_rs2 <= ID_rs2;
            ID_EX_rd <= ID_rd;
            ID_EX_funct3 <= ID_funct3;
            ID_EX_funct7_5 <= ID_funct7_5;
            ID_EX_ALUSrc <= ID_ALUSrc;
            ID_EX_MemWrite <= ID_MemWrite;
            ID_EX_RegWrite <= ID_RegWrite;
            ID_EX_Branch <= ID_Branch;
            ID_EX_ALUOp <= ID_ALUOp;
            ID_EX_ResultSrc <= ID_ResultSrc;
        end
    end

    always @(posedge clk or posedge reset) begin
        if (reset) begin
            EX_MEM_ALUResult <= 0; EX_MEM_WriteData <= 0; EX_MEM_rd <= 0; EX_MEM_MemWrite <= 0; EX_MEM_RegWrite <= 0; EX_MEM_ResultSrc <= 0; EX_MEM_BranchTaken <= 0; EX_MEM_BranchTarget <= 0;
        end else begin
            EX_MEM_ALUResult <= EX_ALUResult;
            EX_MEM_WriteData <= ID_EX_SrcB;
            EX_MEM_rd <= ID_EX_rd;
            EX_MEM_MemWrite <= ID_EX_MemWrite;
            EX_MEM_RegWrite <= ID_EX_RegWrite;
            EX_MEM_ResultSrc <= ID_EX_ResultSrc;
            EX_MEM_BranchTaken <= EX_BranchTaken;
            EX_MEM_BranchTarget <= EX_BranchTarget;
        end
    end

    always @(posedge clk or posedge reset) begin
        if (reset) begin
            MEM_WB_ReadData <= 0; MEM_WB_ALUResult <= 0; MEM_WB_rd <= 0; MEM_WB_RegWrite <= 0; MEM_WB_ResultSrc <= 0;
        end else begin
            MEM_WB_ReadData <= MEM_ReadData;
            MEM_WB_ALUResult <= EX_MEM_ALUResult;
            MEM_WB_rd <= EX_MEM_rd;
            MEM_WB_RegWrite <= EX_MEM_RegWrite;
            MEM_WB_ResultSrc <= EX_MEM_ResultSrc;
        end
    end

    always @(*) begin
        MEM_WB_RegWrite = MEM_WB_RegWrite; 
    end

endmodule

single_cycle_cpu_tb.v
module single_cycle_cpu_tb;
    reg clk;
    reg reset;

    // single_cycle_cpu uut (
    //     .clk(clk),
    //     .reset(reset)
    // );

    full_pipeline uut (
        .clk(clk),
        .reset(reset)
    );

    initial begin
        $dumpfile("single_cycle_cpu_tb.vcd");
        $dumpvars(0, uut);

        clk = 0;
        reset = 1;
        #10; reset = 0;

        #500 $finish;
    end

    always #5 clk = ~clk;
endmodule

single_cycle_cpu_tb.vcd
$date
	Wed Oct 29 21:29:49 2025
$end
$version
	Icarus Verilog
$end
$timescale
	1s
$end
$scope module single_cycle_cpu_tb $end
$scope module uut $end
$var wire 1 ! EX_BranchTaken $end
$var wire 1 " clk $end
$var wire 1 # reset $end
$var wire 32 $ WB_Result [31:0] $end
$var wire 32 % RF_RD2 [31:0] $end
$var wire 32 & RF_RD1 [31:0] $end
$var wire 32 ' PCPlus4 [31:0] $end
$var wire 32 ( PCNext [31:0] $end
$var wire 32 ) PC [31:0] $end
$var wire 32 * MEM_ReadData [31:0] $end
$var wire 32 + InstrIF [31:0] $end
$var wire 5 , ID_rs2 [4:0] $end
$var wire 5 - ID_rs1 [4:0] $end
$var wire 5 . ID_rd [4:0] $end
$var wire 7 / ID_opcode [6:0] $end
$var wire 1 0 ID_funct7_5 $end
$var wire 3 1 ID_funct3 [2:0] $end
$var wire 2 2 ID_ResultSrc [1:0] $end
$var wire 1 3 ID_RegWrite $end
$var wire 1 4 ID_MemWrite $end
$var wire 2 5 ID_ImmSrc [1:0] $end
$var wire 32 6 ID_ImmExt [31:0] $end
$var wire 1 7 ID_Branch $end
$var wire 1 8 ID_ALUSrc $end
$var wire 2 9 ID_ALUOp [1:0] $end
$var wire 1 : EX_Zero $end
$var wire 32 ; EX_SrcB [31:0] $end
$var wire 32 < EX_BranchTarget [31:0] $end
$var wire 32 = EX_ALUResult [31:0] $end
$var wire 4 > EX_ALUControl [3:0] $end
$var reg 32 ? EX_MEM_ALUResult [31:0] $end
$var reg 1 @ EX_MEM_BranchTaken $end
$var reg 32 A EX_MEM_BranchTarget [31:0] $end
$var reg 1 B EX_MEM_MemWrite $end
$var reg 1 C EX_MEM_RegWrite $end
$var reg 2 D EX_MEM_ResultSrc [1:0] $end
$var reg 32 E EX_MEM_WriteData [31:0] $end
$var reg 5 F EX_MEM_rd [4:0] $end
$var reg 2 G ID_EX_ALUOp [1:0] $end
$var reg 1 H ID_EX_ALUSrc $end
$var reg 1 I ID_EX_Branch $end
$var reg 32 J ID_EX_Imm [31:0] $end
$var reg 1 K ID_EX_MemWrite $end
$var reg 32 L ID_EX_PC [31:0] $end
$var reg 1 M ID_EX_RegWrite $end
$var reg 2 N ID_EX_ResultSrc [1:0] $end
$var reg 32 O ID_EX_SrcA [31:0] $end
$var reg 32 P ID_EX_SrcB [31:0] $end
$var reg 3 Q ID_EX_funct3 [2:0] $end
$var reg 1 R ID_EX_funct7_5 $end
$var reg 5 S ID_EX_rd [4:0] $end
$var reg 5 T ID_EX_rs1 [4:0] $end
$var reg 5 U ID_EX_rs2 [4:0] $end
$var reg 32 V IF_ID_Instr [31:0] $end
$var reg 32 W IF_ID_PC [31:0] $end
$var reg 32 X MEM_WB_ALUResult [31:0] $end
$var reg 32 Y MEM_WB_ReadData [31:0] $end
$var reg 1 Z MEM_WB_RegWrite $end
$var reg 2 [ MEM_WB_ResultSrc [1:0] $end
$var reg 5 \ MEM_WB_rd [4:0] $end
$scope module ad $end
$var wire 2 ] ALUOp [1:0] $end
$var wire 1 ^ RtypeSub $end
$var wire 3 _ funct3 [2:0] $end
$var wire 1 R funct7b5 $end
$var wire 1 ` opb5 $end
$var reg 4 a ALUControl [3:0] $end
$upscope $end
$scope module alu_unit $end
$var wire 4 b ALUControl [3:0] $end
$var wire 32 c ALUResult [31:0] $end
$var wire 32 d SrcA [31:0] $end
$var wire 32 e SrcB [31:0] $end
$var wire 32 f temp [31:0] $end
$var wire 1 g sltu $end
$var wire 1 h slt $end
$var wire 1 : Zero $end
$var wire 1 i V $end
$var wire 32 j Sum [31:0] $end
$var reg 32 k ResultReg [31:0] $end
$upscope $end
$scope module dmem $end
$var wire 32 l A [31:0] $end
$var wire 1 B MemWrite $end
$var wire 32 m RD [31:0] $end
$var wire 32 n WD [31:0] $end
$var wire 1 " clk $end
$var integer 32 o i [31:0] $end
$upscope $end
$scope module imem $end
$var wire 32 p RD [31:0] $end
$var wire 32 q A [31:0] $end
$var integer 32 r i [31:0] $end
$upscope $end
$scope module immgen $end
$var wire 32 s ImmExt [31:0] $end
$var wire 25 t Instr [31:7] $end
$var wire 2 u ImmSrc [1:0] $end
$var reg 32 v ImmExtReg [31:0] $end
$upscope $end
$scope module md $end
$var wire 7 w op [6:0] $end
$var reg 2 x ALUOp [1:0] $end
$var reg 1 8 ALUSrc $end
$var reg 1 7 Branch $end
$var reg 2 y ImmSrc [1:0] $end
$var reg 1 z Jump $end
$var reg 1 4 MemWrite $end
$var reg 1 3 RegWrite $end
$var reg 2 { ResultSrc [1:0] $end
$upscope $end
$scope module pc_reg $end
$var wire 32 | PCNext [31:0] $end
$var wire 1 " clk $end
$var wire 1 # reset $end
$var wire 32 } PC [31:0] $end
$var reg 32 ~ PCReg [31:0] $end
$upscope $end
$scope module rf $end
$var wire 5 !" A1 [4:0] $end
$var wire 5 "" A2 [4:0] $end
$var wire 5 #" A3 [4:0] $end
$var wire 32 $" WD3 [31:0] $end
$var wire 1 Z WE3 $end
$var wire 1 " clk $end
$var wire 1 # reset $end
$var wire 32 %" RD2 [31:0] $end
$var wire 32 &" RD1 [31:0] $end
$scope begin $unm_blk_31 $end
$var integer 32 '" i [31:0] $end
$upscope $end
$upscope $end
$upscope $end
$upscope $end
$enddefinitions $end
$comment Show the parameter values. $end
$dumpall
$end
#0
$dumpvars
b100000 '"
b0 &"
b0 %"
b0 $"
b0 #"
b0 ""
b0 !"
b0 ~
b0 }
b100 |
b0 {
0z
b0 y
b0 x
b0 w
b0 v
b0 u
b0 t
b0 s
b10000000000 r
b0 q
b101000000000001010010011 p
b10000000000000000 o
b0 n
b0 m
b0 l
b0 k
b0 j
0i
0h
0g
b0 f
b0 e
b0 d
b0 c
b0 b
b0 a
z`
b0 _
0^
b0 ]
b0 \
b0 [
0Z
b0 Y
b0 X
b0 W
b0 V
b0 U
b0 T
b0 S
0R
b0 Q
b0 P
b0 O
b0 N
0M
b0 L
0K
b0 J
0I
0H
b0 G
b0 F
b0 E
b0 D
0C
0B
b0 A
0@
b0 ?
b0 >
b0 =
b0 <
b0 ;
1:
b0 9
08
07
b0 6
b0 5
04
03
b0 2
b0 1
00
b0 /
b0 .
b0 -
b0 ,
b101000000000001010010011 +
b0 *
b0 )
b100 (
b100 '
b0 &
b0 %
b0 $
1#
0"
0!
$end
#5
b100000 '"
1"
#10
0"
0#
#15
b10 9
b10 x
18
13
b1010 6
b1010 s
b1010 v
b1100010011 +
b1100010011 p
b1000 (
b1000 |
b10011 /
b10011 w
b1010 ,
b1010 ""
b101 .
b10100000000000101 t
b1000 '
b100 )
b100 q
b100 }
b100 ~
b101000000000001010010011 V
1"
#20
0"
#25
0:
b1010 =
b1010 c
b1010 k
b1010 j
b1010 f
1h
b0 6
b0 s
b0 v
1g
b1010 ;
b1010 e
b0 ,
b0 ""
b110 .
b110 t
b1110010011 +
b1110010011 p
b1100 (
b1100 |
b10 G
b10 ]
1M
1H
b101 S
b1010 U
b1010 <
b1010 J
b1100010011 V
b100 W
b1100 '
b1000 )
b1000 q
b1000 }
b1000 ~
1"
#30
0"
#35
1:
b0 =
b0 c
b0 k
b0 j
b0 f
0h
b101000101001100011 +
b101000101001100011 p
b10000 (
b10000 |
b111 .
b111 t
0g
b0 ;
b0 e
b10 *
b10 m
b10000 '
b1100 )
b1100 q
b1100 }
b1100 ~
b1110010011 V
b1000 W
b110 S
b0 U
b0 J
b100 <
b100 L
b1010 A
1C
b101 F
b1010 ?
b1010 l
1"
#40
0"
#45
b10100 6
b10100 s
b10100 v
b1 9
b1 x
17
08
b10 5
b10 u
b10 y
03
b1010 $
b1010 $"
b0 *
b0 m
b1100011 /
b1100011 w
b101 -
b101 !"
b10100 .
b10100010100 t
b111010111000000011 +
b111010111000000011 p
b10100 (
b10100 |
1Z
b101 \
b101 #"
b1010 X
b10 Y
b100 A
b110 F
b0 ?
b0 l
b111 S
b1000 <
b1000 L
b101000101001100011 V
b1100 W
b10100 '
b10000 )
b10000 q
b10000 }
b10000 ~
1"
#50
0"
#55
1:
b0 =
b0 c
b0 k
b11111111111111111111111111111111 f
b0 9
b0 x
07
b1 2
b1 {
18
b0 5
b0 u
b0 y
13
b0 6
b0 s
b0 v
b0 j
b1110000110000001100110011 +
b1110000110000001100110011 p
b100000 (
b100000 |
b11 /
b11 w
b111 -
b111 !"
b11100 .
b10 1
b11101011100 t
b1 >
b1 a
b1 b
1!
b0 $
b0 $"
b0 &
b0 &"
b11000 '
b10100 )
b10100 q
b10100 }
b10100 ~
b111010111000000011 V
b10000 W
b1 G
b1 ]
1I
0M
0H
b10100 S
b101 T
b10100 J
b100000 <
b1100 L
b1000 A
b111 F
b110 \
b110 #"
b0 X
b0 Y
1"
#60
0"
#65
1:
b0 =
b0 c
b0 k
b0 f
b0 j
b10 9
b10 x
b0 2
b0 {
08
bx 5
bx u
bx y
bx 6
bx s
bx v
0!
b0 >
b0 a
b0 b
b100100 (
b100100 |
b110011 /
b110011 w
b110 -
b110 !"
b11100 ,
b11100 ""
b110 .
b0 1
b111000011000000110 t
b1101100011 +
b1101100011 p
b111 \
b111 #"
b100000 A
1@
0C
b10100 F
b1 N
b0 G
b0 ]
0I
1M
1H
b10 Q
b10 _
b11100 S
b111 T
b0 J
b10000 <
b10000 L
b1110000110000001100110011 V
b10100 W
b100100 '
b100000 )
b100000 q
b100000 }
b100000 ~
1"
#70
0"
#75
b110 6
b110 s
b110 v
b1 9
b1 x
17
b10 5
b10 u
b10 y
03
b10011 +
b10011 p
b101000 (
b101000 |
b1100011 /
b1100011 w
b0 -
b0 !"
b0 ,
b0 ""
b110 t
b101000 '
b100100 )
b100100 q
b100100 }
b100100 ~
b1101100011 V
b100000 W
b0 N
b10 G
b10 ]
0H
b0 Q
b0 _
b110 S
b11100 U
b110 T
bx J
bx <
b10100 L
b10000 A
0@
b1 D
1C
b11100 F
0Z
b10100 \
b10100 #"
1"
#80
0"
#85
1:
b0 =
b0 c
b0 k
b11111111111111111111111111111111 f
b0 j
b10 9
b10 x
07
18
b0 5
b0 u
b0 y
13
b0 6
b0 s
b0 v
b1 >
b1 a
b1 b
1!
b10011 /
b10011 w
b0 .
b0 t
b11111100000000000000111011100011 +
b11111100000000000000111011100011 p
b100110 (
b100110 |
b1 [
1Z
b11100 \
b11100 #"
bx A
b0 D
b110 F
b1 G
b1 ]
1I
0M
b0 U
b0 T
b100110 <
b110 J
b100000 L
b10011 V
b100100 W
b101100 '
b101000 )
b101000 q
b101000 }
b101000 ~
1"
#90
0"
#95
1:
b0 =
b0 c
b0 k
b0 f
b1 9
b1 x
17
08
b10 5
b10 u
b10 y
03
b11111111111111111111111111011100 6
b11111111111111111111111111011100 s
b11111111111111111111111111011100 v
b0 j
b10011 +
b10011 p
b1100011 /
b1100011 w
b11101 .
10
b1111110000000000000011101 t
b0 >
b0 a
b0 b
0!
b101010 (
b101010 |
b101010 '
b100110 )
b100110 q
b100110 }
b100110 ~
b11111100000000000000111011100011 V
b101000 W
b10 G
b10 ]
0I
1M
1H
b0 S
b0 J
b100100 <
b100100 L
b100110 A
1@
0C
b0 [
b110 \
b110 #"
1"
#100
0"
#105
1:
b0 =
b0 c
b0 k
b11111111111111111111111111111111 f
b0 j
b10 9
b10 x
07
18
b0 5
b0 u
b0 y
13
b0 6
b0 s
b0 v
b1 >
b1 a
b1 b
1!
x^
b10011 /
b10011 w
b0 .
00
b0 t
b11111100000000000000111011100011 +
b11111100000000000000111011100011 p
b100 (
b100 |
0Z
b100100 A
0@
1C
b0 F
b1 G
b1 ]
1I
0M
0H
1R
b11101 S
b11111111111111111111111111011100 J
b100 <
b101000 L
b10011 V
b100110 W
b101110 '
b101010 )
b101010 q
b101010 }
b101010 ~
1"
#110
0"
#115
1:
b0 =
b0 c
b0 k
b0 f
b1 9
b1 x
17
08
b10 5
b10 u
b10 y
03
b11111111111111111111111111011100 6
b11111111111111111111111111011100 s
b11111111111111111111111111011100 v
b0 j
b1100010011 +
b1100010011 p
b1100011 /
b1100011 w
b11101 .
10
b1111110000000000000011101 t
b0 >
b0 a
b0 b
0!
0^
b1000 (
b1000 |
b1000 '
b100 )
b100 q
b100 }
b100 ~
b11111100000000000000111011100011 V
b101010 W
b10 G
b10 ]
0I
1M
1H
0R
b0 S
b0 J
b100110 <
b100110 L
b100 A
1@
0C
b11101 F
1Z
b0 \
b0 #"
1"
#120
0"
#125
1:
b0 =
b0 c
b0 k
b11111111111111111111111111111111 f
b0 j
b10 9
b10 x
07
18
b0 5
b0 u
b0 y
13
b0 6
b0 s
b0 v
b1 >
b1 a
b1 b
1!
x^
b10011 /
b10011 w
b110 .
00
b110 t
b1110010011 +
b1110010011 p
b110 (
b110 |
0Z
b11101 \
b11101 #"
b100110 A
0@
1C
b0 F
b1 G
b1 ]
1I
0M
0H
1R
b11101 S
b11111111111111111111111111011100 J
b110 <
b101010 L
b1100010011 V
b100 W
b1100 '
b1000 )
b1000 q
b1000 }
b1000 ~
1"
#130
0"
#135
1:
b0 =
b0 c
b0 k
b0 f
b0 j
b1100010011 +
b1100010011 p
b111 .
b111 t
b0 >
b0 a
b0 b
0!
0^
b1010 (
b1010 |
b1010 '
b110 )
b110 q
b110 }
b110 ~
b1110010011 V
b1000 W
b10 G
b10 ]
0I
1M
1H
0R
b110 S
b0 J
b100 <
b100 L
b110 A
1@
0C
b11101 F
1Z
b0 \
b0 #"
1"
#140
0"
#145
b110 .
b110 t
b1110010011 +
b1110010011 p
b1110 (
b1110 |
0Z
b11101 \
b11101 #"
b100 A
0@
1C
b110 F
b111 S
b1000 <
b1000 L
b1100010011 V
b110 W
b1110 '
b1010 )
b1010 q
b1010 }
b1010 ~
1"
#150
0"
